rattr/__init__.py
rattr/__main__.py
rattr/_version.py
rattr/analyser/__init__.py
rattr/analyser/annotations.py
rattr/analyser/base.py
rattr/analyser/cls.py
rattr/analyser/exc.py
rattr/analyser/file.py
rattr/analyser/function.py
rattr/analyser/types.py
rattr/analyser/util.py
rattr/ast/__init__.py
rattr/ast/_util.py
rattr/ast/types.py
rattr/ast/util.py
rattr/cli/__init__.py
rattr/cli/_argparse.py
rattr/cli/_arguments.py
rattr/cli/_types.py
rattr/cli/_util.py
rattr/cli/_validate.py
rattr/cli/exit_codes.py
rattr/cli/parser.py
rattr/cli/toml.py
rattr/codegen/__init__.py
rattr/codegen/util.py
rattr/config/__init__.py
rattr/config/_types.py
rattr/config/_util.py
rattr/config/state.py
rattr/config/util.py
rattr/error/__init__.py
rattr/error/error.py
rattr/error/exc.py
rattr/extra/__init__.py
rattr/extra/_dict_changes.py
rattr/extra/functools.py
rattr/models/__init__.py
rattr/models/plugins.py
rattr/models/types.py
rattr/models/context/__init__.py
rattr/models/context/_context.py
rattr/models/context/_root_context.py
rattr/models/context/_symbol_table.py
rattr/models/context/_util.py
rattr/models/ir/__init__.py
rattr/models/ir/file.py
rattr/models/ir/function.py
rattr/models/results/__init__.py
rattr/models/results/cacheable.py
rattr/models/results/file.py
rattr/models/results/function.py
rattr/models/results/util.py
rattr/models/symbol/__init__.py
rattr/models/symbol/_symbol.py
rattr/models/symbol/_symbols.py
rattr/models/symbol/_types.py
rattr/models/symbol/_util.py
rattr/models/symbol/util.py
rattr/models/util/__init__.py
rattr/models/util/_serialisation_helpers.py
rattr/models/util/_types.py
rattr/models/util/hash.py
rattr/models/util/serialise.py
rattr/module_locator/__init__.py
rattr/module_locator/_locate.py
rattr/module_locator/exc.py
rattr/module_locator/models.py
rattr/module_locator/types.py
rattr/module_locator/util.py
rattr/plugins/__init__.py
rattr/plugins/analysers/__init__.py
rattr/plugins/analysers/builtins.py
rattr/plugins/analysers/collections.py
rattr-0.2.4.dist-info/LICENSE
rattr-0.2.4.dist-info/METADATA
rattr-0.2.4.dist-info/WHEEL
rattr-0.2.4.dist-info/entry_points.txt
rattr-0.2.4.dist-info/top_level.txt
rattr-0.2.4.dist-info/RECORD
