Metadata-Version: 2.2
Name: rattr
Version: 0.2.4
Summary: Rattr rats on your attrs.
Home-page: https://github.com/SuadeLabs/rattr
Author: Suade Labs, Brandon Harris
Author-email: brandon@saude.org, bpharris@pm.me
Maintainer: Brandon Harris
Maintainer-email: brandon@saude.org, bpharris@pm.me
License: MIT
Keywords: automation linting type-checking attributes rats
Classifier: Environment :: Console
Classifier: Intended Audience :: Developers
Classifier: License :: OSI Approved :: MIT License
Classifier: Operating System :: OS Independent
Classifier: Programming Language :: Python
Classifier: Programming Language :: Python :: 3.9
Classifier: Programming Language :: Python :: 3.10
Classifier: Programming Language :: Python :: 3.11
Classifier: Programming Language :: Python :: 3.12
Classifier: Programming Language :: Python :: 3 :: Only
Classifier: Topic :: Software Development :: Libraries :: Python Modules
Classifier: Topic :: Software Development :: Quality Assurance
Requires-Python: >=3.9
License-File: LICENSE
Requires-Dist: isort>=5.13.2
Requires-Dist: tomli>=1.2.3; python_version < "3.11"
Requires-Dist: attrs<=24,>=21
Requires-Dist: cattrs<=24,>=21
Requires-Dist: frozendict>=2.4.0
Provides-Extra: dev
Requires-Dist: pytest>=8.0.0; extra == "dev"
Requires-Dist: ruff==0.2.1; extra == "dev"
Dynamic: author
Dynamic: author-email
Dynamic: classifier
Dynamic: description
Dynamic: description-content-type
Dynamic: home-page
Dynamic: keywords
Dynamic: license
Dynamic: maintainer
Dynamic: maintainer-email
Dynamic: provides-extra
Dynamic: requires-dist
Dynamic: requires-python
Dynamic: summary
